ws/nginxdbauth/__init__.py
ws/nginxdbauth/web.py
ws/nginxdbauth/tests/__init__.py
ws/nginxdbauth/tests/test_web.py
ws.nginxdbauth-1.1.1.dist-info/METADATA
ws.nginxdbauth-1.1.1.dist-info/WHEEL
ws.nginxdbauth-1.1.1.dist-info/entry_points.txt
ws.nginxdbauth-1.1.1.dist-info/licenses/LICENSE
ws.nginxdbauth-1.1.1.dist-info/RECORD
