Metadata-Version: 2.3
Name: ws.nginxdbauth
Version: 1.1.1
Summary: Authenticate an nginx request against an SQL database
Project-URL: Repository, https://github.com/wosc/nginx-db-auth
Author-email: Wolfgang Schnerring <wosc@wosc.de>
License:  BSD-3-Clause
License-File: LICENSE
Requires-Python: >=3.7
Requires-Dist: flask
Requires-Dist: sqlalchemy>=2.0.0
Provides-Extra: test
Requires-Dist: passlib; extra == 'test'
Requires-Dist: pytest; extra == 'test'
Requires-Dist: pytest-cov; extra == 'test'
